{
    "avg": {
        "wmc": 6.84,
        "ccn": 4.27,
        "bugs": 0.11,
        "kanDefect": 0.46,
        "relativeSystemComplexity": 96.25,
        "relativeDataComplexity": 2.29,
        "relativeStructuralComplexity": 93.96,
        "volume": 342.89,
        "commentWeight": 35.89,
        "intelligentContent": 53.58,
        "lcom": 1.16,
        "instability": 0.56,
        "afferentCoupling": 1.82,
        "efferentCoupling": 2.84,
        "difficulty": 5.31,
        "mi": 99.77,
        "distance": 0.26,
        "incomingCDep": 2.71,
        "incomingPDep": 1.14,
        "outgoingCDep": 5.57,
        "outgoingPDep": 2.71,
        "classesPerPackage": 7.14
    },
    "sum": {
        "loc": 3089,
        "cloc": 1032,
        "lloc": 2063,
        "nbMethods": 161,
        "nbClasses": 45,
        "nbInterfaces": 5,
        "nbPackages": 7,
        "violations": {
            "total": 7,
            "information": 0,
            "warning": 7,
            "error": 0,
            "critical": 0
        }
    }
}